ua_spoofer.py
ua_spoofer-1.0.dist-info/COPYING
ua_spoofer-1.0.dist-info/METADATA
ua_spoofer-1.0.dist-info/WHEEL
ua_spoofer-1.0.dist-info/top_level.txt
ua_spoofer-1.0.dist-info/RECORD
