Metadata-Version: 2.1
Name: ua-spoofer
Version: 1.0
Summary: A module for collecting and providing popular user agent strings, with a requests session which rotates user agents.
Home-page: https://gitlab.com/odg/ua_spoofer
Author: Oliver Galvin
Author-email: odg@riseup.com
License: Apache-2.0
Keywords: user agent string spoofer spoofing random scraping crawling crawler bot
Platform: UNKNOWN
Classifier: Development Status :: 4 - Beta
Classifier: Intended Audience :: Developers
Classifier: License :: OSI Approved :: Apache Software License
Classifier: Operating System :: OS Independent
Classifier: Programming Language :: Python :: 3.5
Classifier: Programming Language :: Python :: 3.6
Classifier: Programming Language :: Python :: 3.7
Classifier: Topic :: Internet :: WWW/HTTP
Requires-Python: >=3
Requires-Dist: beautifulsoup4
Requires-Dist: requests
